{
  "updated_at": "2026-04-07T08:07:33.357Z",
  "data_date": "2026-04-06",
  "group": {
    "id": "group-hoodie-core",
    "name": "AMJ010095智能托管组",
    "macroGoal": "boost-sales",
    "targetAcos": 20
  },
  "days": [
    {
      "date": "2026-03-31",
      "orders": 11,
      "salesVolume": 11,
      "spend": 21.19,
      "sales": 244.49,
      "acos": 8.7,
      "impressions": 5114,
      "clicks": 77,
      "ctr": 1.51,
      "cvr": 14.29
    },
    {
      "date": "2026-04-01",
      "orders": 1,
      "salesVolume": 1,
      "spend": 6.58,
      "sales": 17.99,
      "acos": 36.6,
      "impressions": 2569,
      "clicks": 17,
      "ctr": 0.66,
      "cvr": 5.88
    },
    {
      "date": "2026-04-02",
      "orders": 3,
      "salesVolume": 3,
      "spend": 9.6,
      "sales": 53.97,
      "acos": 17.8,
      "impressions": 2844,
      "clicks": 26,
      "ctr": 0.91,
      "cvr": 11.54
    },
    {
      "date": "2026-04-03",
      "orders": 2,
      "salesVolume": 2,
      "spend": 9.63,
      "sales": 37.98,
      "acos": 25.4,
      "impressions": 2870,
      "clicks": 29,
      "ctr": 1.01,
      "cvr": 6.9
    },
    {
      "date": "2026-04-04",
      "orders": 2,
      "salesVolume": 2,
      "spend": 11.05,
      "sales": 35.98,
      "acos": 30.7,
      "impressions": 2894,
      "clicks": 30,
      "ctr": 1.04,
      "cvr": 6.67
    },
    {
      "date": "2026-04-05",
      "orders": 2,
      "salesVolume": 2,
      "spend": 12.3,
      "sales": 35.98,
      "acos": 34.2,
      "impressions": 4170,
      "clicks": 35,
      "ctr": 0.84,
      "cvr": 5.71
    },
    {
      "date": "2026-04-06",
      "orders": 1,
      "salesVolume": 1,
      "spend": 15.01,
      "sales": 17.99,
      "acos": 83.4,
      "impressions": 6201,
      "clicks": 39,
      "ctr": 0.63,
      "cvr": 2.56
    }
  ],
  "campaigns": {
    "333903452360072": {
      "name": "TEST-AI-AMJ010095-MANUAL-KEYWORD-BROAD-20260119150235",
      "type": "手动投放",
      "budget": 30,
      "days": [
        {
          "date": "2026-03-31",
          "orders": 1,
          "salesVolume": 1,
          "spend": 1.63,
          "sales": 19.99,
          "acos": 8.15,
          "impressions": 547,
          "clicks": 4,
          "ctr": 0.73,
          "cvr": 25
        },
        {
          "date": "2026-04-01",
          "orders": 0,
          "salesVolume": 0,
          "spend": 2.8,
          "sales": 0,
          "acos": 0,
          "impressions": 441,
          "clicks": 5,
          "ctr": 1.13,
          "cvr": 0
        },
        {
          "date": "2026-04-02",
          "orders": 0,
          "salesVolume": 0,
          "spend": 2.85,
          "sales": 0,
          "acos": 0,
          "impressions": 425,
          "clicks": 6,
          "ctr": 1.41,
          "cvr": 0
        },
        {
          "date": "2026-04-03",
          "orders": 0,
          "salesVolume": 0,
          "spend": 0.4,
          "sales": 0,
          "acos": 0,
          "impressions": 213,
          "clicks": 2,
          "ctr": 0.94,
          "cvr": 0
        },
        {
          "date": "2026-04-04",
          "orders": 0,
          "salesVolume": 0,
          "spend": 1.15,
          "sales": 0,
          "acos": 0,
          "impressions": 178,
          "clicks": 2,
          "ctr": 1.12,
          "cvr": 0
        },
        {
          "date": "2026-04-05",
          "orders": 0,
          "salesVolume": 0,
          "spend": 0.75,
          "sales": 0,
          "acos": 0,
          "impressions": 151,
          "clicks": 2,
          "ctr": 1.32,
          "cvr": 0
        },
        {
          "date": "2026-04-06",
          "orders": 0,
          "salesVolume": 0,
          "spend": 0.15,
          "sales": 0,
          "acos": 0,
          "impressions": 238,
          "clicks": 1,
          "ctr": 0.42,
          "cvr": 0
        }
      ]
    },
    "510273719211911": {
      "name": "TEST-AI-AMJ010095-AUTO-20260119150235",
      "type": "自动投放",
      "budget": 30,
      "days": [
        {
          "date": "2026-03-31",
          "orders": 10,
          "salesVolume": 10,
          "spend": 19.11,
          "sales": 224.5,
          "acos": 8.51,
          "impressions": 4436,
          "clicks": 72,
          "ctr": 1.62,
          "cvr": 13.89
        },
        {
          "date": "2026-04-01",
          "orders": 0,
          "salesVolume": 0,
          "spend": 2.43,
          "sales": 0,
          "acos": 0,
          "impressions": 1933,
          "clicks": 9,
          "ctr": 0.47,
          "cvr": 0
        },
        {
          "date": "2026-04-02",
          "orders": 3,
          "salesVolume": 3,
          "spend": 5.85,
          "sales": 53.97,
          "acos": 10.84,
          "impressions": 2211,
          "clicks": 18,
          "ctr": 0.81,
          "cvr": 16.67
        },
        {
          "date": "2026-04-03",
          "orders": 1,
          "salesVolume": 1,
          "spend": 8.78,
          "sales": 17.99,
          "acos": 48.8,
          "impressions": 2516,
          "clicks": 26,
          "ctr": 1.03,
          "cvr": 3.85
        },
        {
          "date": "2026-04-04",
          "orders": 2,
          "salesVolume": 2,
          "spend": 9.45,
          "sales": 35.98,
          "acos": 26.26,
          "impressions": 2569,
          "clicks": 27,
          "ctr": 1.05,
          "cvr": 7.41
        },
        {
          "date": "2026-04-05",
          "orders": 2,
          "salesVolume": 2,
          "spend": 11.55,
          "sales": 35.98,
          "acos": 32.1,
          "impressions": 3837,
          "clicks": 33,
          "ctr": 0.86,
          "cvr": 6.06
        },
        {
          "date": "2026-04-06",
          "orders": 1,
          "salesVolume": 1,
          "spend": 14.06,
          "sales": 17.99,
          "acos": 78.15,
          "impressions": 5795,
          "clicks": 36,
          "ctr": 0.62,
          "cvr": 2.78
        }
      ]
    },
    "476971790430984": {
      "name": "TEST-AI-AMJ010095-MANUAL-PRODUCT-EXPANDED-20260119150235",
      "type": "手动投放",
      "budget": 12,
      "days": [
        {
          "date": "2026-03-31",
          "orders": 0,
          "salesVolume": 0,
          "spend": 0.45,
          "sales": 0,
          "acos": 0,
          "impressions": 131,
          "clicks": 1,
          "ctr": 0.76,
          "cvr": 0
        },
        {
          "date": "2026-04-01",
          "orders": 1,
          "salesVolume": 1,
          "spend": 1.35,
          "sales": 17.99,
          "acos": 7.5,
          "impressions": 195,
          "clicks": 3,
          "ctr": 1.54,
          "cvr": 33.33
        },
        {
          "date": "2026-04-02",
          "orders": 0,
          "salesVolume": 0,
          "spend": 0.9,
          "sales": 0,
          "acos": 0,
          "impressions": 208,
          "clicks": 2,
          "ctr": 0.96,
          "cvr": 0
        },
        {
          "date": "2026-04-03",
          "orders": 1,
          "salesVolume": 1,
          "spend": 0.45,
          "sales": 19.99,
          "acos": 2.25,
          "impressions": 141,
          "clicks": 1,
          "ctr": 0.71,
          "cvr": 100
        },
        {
          "date": "2026-04-04",
          "orders": 0,
          "salesVolume": 0,
          "spend": 0.45,
          "sales": 0,
          "acos": 0,
          "impressions": 147,
          "clicks": 1,
          "ctr": 0.68,
          "cvr": 0
        },
        {
          "date": "2026-04-05",
          "orders": 0,
          "salesVolume": 0,
          "spend": 0,
          "sales": 0,
          "acos": 0,
          "impressions": 182,
          "clicks": 0,
          "ctr": 0,
          "cvr": 0
        },
        {
          "date": "2026-04-06",
          "orders": 0,
          "salesVolume": 0,
          "spend": 0.8,
          "sales": 0,
          "acos": 0,
          "impressions": 168,
          "clicks": 2,
          "ctr": 1.19,
          "cvr": 0
        }
      ]
    },
    "367851579653868": {
      "name": "TEST-AI-AMJ010095-MANUAL-PRODUCT-CATEGORY-20260119150235",
      "type": "手动投放",
      "budget": 5,
      "days": [
        {
          "date": "2026-03-31",
          "orders": 0,
          "salesVolume": 0,
          "spend": 0,
          "sales": 0,
          "acos": 0,
          "impressions": 0,
          "clicks": 0,
          "ctr": 0,
          "cvr": 0
        },
        {
          "date": "2026-04-01",
          "orders": 0,
          "salesVolume": 0,
          "spend": 0,
          "sales": 0,
          "acos": 0,
          "impressions": 0,
          "clicks": 0,
          "ctr": 0,
          "cvr": 0
        },
        {
          "date": "2026-04-02",
          "orders": 0,
          "salesVolume": 0,
          "spend": 0,
          "sales": 0,
          "acos": 0,
          "impressions": 0,
          "clicks": 0,
          "ctr": 0,
          "cvr": 0
        },
        {
          "date": "2026-04-03",
          "orders": 0,
          "salesVolume": 0,
          "spend": 0,
          "sales": 0,
          "acos": 0,
          "impressions": 0,
          "clicks": 0,
          "ctr": 0,
          "cvr": 0
        },
        {
          "date": "2026-04-04",
          "orders": 0,
          "salesVolume": 0,
          "spend": 0,
          "sales": 0,
          "acos": 0,
          "impressions": 0,
          "clicks": 0,
          "ctr": 0,
          "cvr": 0
        },
        {
          "date": "2026-04-05",
          "orders": 0,
          "salesVolume": 0,
          "spend": 0,
          "sales": 0,
          "acos": 0,
          "impressions": 0,
          "clicks": 0,
          "ctr": 0,
          "cvr": 0
        },
        {
          "date": "2026-04-06",
          "orders": 0,
          "salesVolume": 0,
          "spend": 0,
          "sales": 0,
          "acos": 0,
          "impressions": 0,
          "clicks": 0,
          "ctr": 0,
          "cvr": 0
        }
      ]
    }
  }
}